[
    {
        "%vlocity_namespace%__AttributeCategoryId__c": {
            "%vlocity_namespace%__Code__c": "VLO-ADS",
            "VlocityDataPackType": "VlocityLookupMatchingKeyObject",
            "VlocityLookupRecordSourceKey": "%vlocity_namespace%__AttributeCategory__c/VLO-ADS",
            "VlocityRecordSObjectType": "%vlocity_namespace%__AttributeCategory__c"
        },
        "%vlocity_namespace%__AttributeId__c": {
            "%vlocity_namespace%__Code__c": "ADS-RATE-TYPE",
            "VlocityDataPackType": "VlocityLookupMatchingKeyObject",
            "VlocityLookupRecordSourceKey": "%vlocity_namespace%__Attribute__c/ADS-RATE-TYPE",
            "VlocityRecordSObjectType": "%vlocity_namespace%__Attribute__c"
        },
        "%vlocity_namespace%__GlobalKey__c": "8c78629f-f99f-51fc-9f50-afd6e553f981",
        "%vlocity_namespace%__IsActive__c": true,
        "%vlocity_namespace%__ObjectClassId__c": {
            "%vlocity_namespace%__GlobalKey__c": "63ba6ae5f8c257f7cdccc385d2a85dca",
            "VlocityDataPackType": "VlocityLookupMatchingKeyObject",
            "VlocityLookupRecordSourceKey": "%vlocity_namespace%__ObjectClass__c/63ba6ae5f8c257f7cdccc385d2a85dca",
            "VlocityRecordSObjectType": "%vlocity_namespace%__ObjectClass__c"
        },
        "%vlocity_namespace%__ObjectType__c": "Product2",
        "%vlocity_namespace%__SubClassId__c": {
            "%vlocity_namespace%__GlobalKey__c": "a23a94d9-6560-3836-6149-25c137a28cae",
            "VlocityDataPackType": "VlocityMatchingKeyObject",
            "VlocityMatchingRecordSourceKey": "Product2/a23a94d9-6560-3836-6149-25c137a28cae",
            "VlocityRecordSObjectType": "Product2"
        },
        "Name": "8c78629f-f99f-51fc-9f50-afd6e553f981",
        "VlocityDataPackType": "SObject",
        "VlocityRecordSObjectType": "%vlocity_namespace%__ObjectFieldAttribute__c"
    },
    {
        "%vlocity_namespace%__AttributeCategoryId__c": {
            "%vlocity_namespace%__Code__c": "VLO-ADS",
            "VlocityDataPackType": "VlocityLookupMatchingKeyObject",
            "VlocityLookupRecordSourceKey": "%vlocity_namespace%__AttributeCategory__c/VLO-ADS",
            "VlocityRecordSObjectType": "%vlocity_namespace%__AttributeCategory__c"
        },
        "%vlocity_namespace%__AttributeId__c": {
            "%vlocity_namespace%__Code__c": "Brand",
            "VlocityDataPackType": "VlocityLookupMatchingKeyObject",
            "VlocityLookupRecordSourceKey": "%vlocity_namespace%__Attribute__c/Brand",
            "VlocityRecordSObjectType": "%vlocity_namespace%__Attribute__c"
        },
        "%vlocity_namespace%__GlobalKey__c": "a7224011-7df7-4ef6-6525-e2c44626de74",
        "%vlocity_namespace%__IsActive__c": true,
        "%vlocity_namespace%__ObjectClassId__c": {
            "%vlocity_namespace%__GlobalKey__c": "63ba6ae5f8c257f7cdccc385d2a85dca",
            "VlocityDataPackType": "VlocityLookupMatchingKeyObject",
            "VlocityLookupRecordSourceKey": "%vlocity_namespace%__ObjectClass__c/63ba6ae5f8c257f7cdccc385d2a85dca",
            "VlocityRecordSObjectType": "%vlocity_namespace%__ObjectClass__c"
        },
        "%vlocity_namespace%__ObjectType__c": "Product2",
        "%vlocity_namespace%__SubClassId__c": {
            "%vlocity_namespace%__GlobalKey__c": "a23a94d9-6560-3836-6149-25c137a28cae",
            "VlocityDataPackType": "VlocityMatchingKeyObject",
            "VlocityMatchingRecordSourceKey": "Product2/a23a94d9-6560-3836-6149-25c137a28cae",
            "VlocityRecordSObjectType": "Product2"
        },
        "Name": "a7224011-7df7-4ef6-6525-e2c44626de74",
        "VlocityDataPackType": "SObject",
        "VlocityRecordSObjectType": "%vlocity_namespace%__ObjectFieldAttribute__c"
    },
    {
        "%vlocity_namespace%__AttributeCategoryId__c": {
            "%vlocity_namespace%__Code__c": "VLO-ADS",
            "VlocityDataPackType": "VlocityLookupMatchingKeyObject",
            "VlocityLookupRecordSourceKey": "%vlocity_namespace%__AttributeCategory__c/VLO-ADS",
            "VlocityRecordSObjectType": "%vlocity_namespace%__AttributeCategory__c"
        },
        "%vlocity_namespace%__AttributeId__c": {
            "%vlocity_namespace%__Code__c": "Edition",
            "VlocityDataPackType": "VlocityLookupMatchingKeyObject",
            "VlocityLookupRecordSourceKey": "%vlocity_namespace%__Attribute__c/Edition",
            "VlocityRecordSObjectType": "%vlocity_namespace%__Attribute__c"
        },
        "%vlocity_namespace%__GlobalKey__c": "483a72ad-f93c-6e47-50a3-84936257dfcc",
        "%vlocity_namespace%__IsActive__c": true,
        "%vlocity_namespace%__ObjectClassId__c": {
            "%vlocity_namespace%__GlobalKey__c": "63ba6ae5f8c257f7cdccc385d2a85dca",
            "VlocityDataPackType": "VlocityLookupMatchingKeyObject",
            "VlocityLookupRecordSourceKey": "%vlocity_namespace%__ObjectClass__c/63ba6ae5f8c257f7cdccc385d2a85dca",
            "VlocityRecordSObjectType": "%vlocity_namespace%__ObjectClass__c"
        },
        "%vlocity_namespace%__ObjectType__c": "Product2",
        "%vlocity_namespace%__SubClassId__c": {
            "%vlocity_namespace%__GlobalKey__c": "a23a94d9-6560-3836-6149-25c137a28cae",
            "VlocityDataPackType": "VlocityMatchingKeyObject",
            "VlocityMatchingRecordSourceKey": "Product2/a23a94d9-6560-3836-6149-25c137a28cae",
            "VlocityRecordSObjectType": "Product2"
        },
        "Name": "483a72ad-f93c-6e47-50a3-84936257dfcc",
        "VlocityDataPackType": "SObject",
        "VlocityRecordSObjectType": "%vlocity_namespace%__ObjectFieldAttribute__c"
    }
]